MANIFEST.in
README.rst
setup.py
docs/HISTORY.rst
docs/INSTALL.rst
docs/LICENSE.GPL
docs/LICENSE.txt
quintagroup/__init__.py
quintagroup.theme.schools.egg-info/PKG-INFO
quintagroup.theme.schools.egg-info/SOURCES.txt
quintagroup.theme.schools.egg-info/dependency_links.txt
quintagroup.theme.schools.egg-info/entry_points.txt
quintagroup.theme.schools.egg-info/namespace_packages.txt
quintagroup.theme.schools.egg-info/not-zip-safe
quintagroup.theme.schools.egg-info/requires.txt
quintagroup.theme.schools.egg-info/top_level.txt
quintagroup/theme/__init__.py
quintagroup/theme/schools/README.txt
quintagroup/theme/schools/__init__.py
quintagroup/theme/schools/configure.zcml
quintagroup/theme/schools/profiles/default/metadata.xml
quintagroup/theme/schools/profiles/default/theme.xml
quintagroup/theme/schools/profiles/default/tinymce.xml
quintagroup/theme/schools/src/image1.jpg
quintagroup/theme/schools/src/image2.jpg
quintagroup/theme/schools/src/image3.jpg
quintagroup/theme/schools/src/image4.jpg
quintagroup/theme/schools/static/extra.html
quintagroup/theme/schools/static/index.html
quintagroup/theme/schools/static/manifest.cfg
quintagroup/theme/schools/static/rules.xml
quintagroup/theme/schools/static/tune.xml
quintagroup/theme/schools/static/css/iefixes.css
quintagroup/theme/schools/static/css/styles.css
quintagroup/theme/schools/static/images/album.png
quintagroup/theme/schools/static/images/bg-header.jpg
quintagroup/theme/schools/static/images/bg-logo.png
quintagroup/theme/schools/static/images/icons-sprite.png
quintagroup/theme/schools/static/images/logoSchools.gif
quintagroup/theme/schools/static/images/pb_close.png
quintagroup/theme/schools/static/images/photo-frame.png
quintagroup/theme/schools/static/images/preview.png
quintagroup/theme/schools/static/images/sprite.png
quintagroup/theme/schools/static/images/content/carousel.jpg
quintagroup/theme/schools/static/images/content/info_icon.gif