Metadata-Version: 1.0
Name: quintagroup.theme.schools
Version: 6.8
Summary: Free Diazo theme for Plone
Home-page: http://themes.quintagroup.com/product/schools
Author: Quintagroup
Author-email: skins@quintagroup.com
License: GPL
Keywords: web zope plone theme diazo quintagroup
Platform: UNKNOWN
Classifier: Framework :: Plone
Classifier: Intended Audience :: Developers
Classifier: Topic :: Software Development :: Libraries :: Python Modules
Classifier: License :: OSI Approved :: GNU General Public License (GPL)
